patan/__init__.py
patan/__version__.py
patan/cli.py
patan/downloader.py
patan/engine.py
patan/exceptions.py
patan/filters.py
patan/middleware.py
patan/patan.py
patan/scheduler.py
patan/spiders.py
patan/utils.py
patan/downloadermws/__init__.py
patan/downloadermws/timeout.py
patan/downloadermws/useragent.py
patan/http/__init__.py
patan/http/request.py
patan/http/response.py
patan/pipelines/__init__.py
patan/settings/__init__.py
patan/settings/default.json
patan/spidermws/__init__.py
patan/spidermws/depth.py
patan/spidermws/httperror.py
patan/templates/project/__init__.py
patan/templates/project/items.tpl
patan/templates/project/middlewares.tpl
patan/templates/project/patan.json
patan/templates/project/pipelines.tpl
patan/templates/project/spiders/__init__.py
patan/templates/spider/default.tpl
Patan-1.0.4.dist-info/LICENSE
Patan-1.0.4.dist-info/METADATA
Patan-1.0.4.dist-info/WHEEL
Patan-1.0.4.dist-info/entry_points.txt
Patan-1.0.4.dist-info/top_level.txt
Patan-1.0.4.dist-info/RECORD
