Metadata-Version: 2.1
Name: Patan
Version: 1.0.4
Summary: A lightweight web crawling framework
Home-page: https://github.com/20perline/patan
Author: 20perline
Author-email: tlhk2@163.com
License: MIT
Project-URL: Source, https://github.com/20perline/patan
Platform: UNKNOWN
Requires-Python: >=3.7
Requires-Dist: aiohttp (>=3.6.2)
Requires-Dist: glom (>=20.5.0)
Requires-Dist: click (>=6.7)
Requires-Dist: aiohttp-sse-client (>=0.2.1)
